README.md
setup.py
autumn/__init__.py
autumn/executor.py
autumn/lib/__init__.py
autumn/lib/process.py
autumn/lib/trigger.py
autumn/utils/__init__.py
autumn/utils/async_pool.py
autumn/utils/decorators.py
autumn/utils/hash.py
autumn/utils/kafka.py
autumn/utils/log.py
autumn/utils/net.py
autumn/utils/process.py
autumn/utils/profiling.py
autumn/utils/runtime.py
autumn/utils/task.py
e_autumn.egg-info/PKG-INFO
e_autumn.egg-info/SOURCES.txt
e_autumn.egg-info/dependency_links.txt
e_autumn.egg-info/requires.txt
e_autumn.egg-info/top_level.txt