Metadata-Version: 1.2
Name: e-autumn
Version: 0.0.32
Summary: A executor framework
Home-page: https://coding.net/u/Alecyrus/p/Autumn
Author: Druggle
Author-email: iamdrug@qq.com
License: UNKNOWN
Keywords: executor
Platform: UNKNOWN
Classifier: Programming Language :: Python :: 3.7
Requires-Python: >=3.7
